fancy_source_query/__init__.py
fancy_source_query/config.py
fancy_source_query/exceptions.py
fancy_source_query/fmt.py
fancy_source_query/guess_map.py
fancy_source_query/interfaces/__init__.py
fancy_source_query/interfaces/cli.py
fancy_source_query/interfaces/nonebot.py
fancy_source_query/querypool/__init__.py
fancy_source_query/querypool/infos.py
fancy_source_query/server_group.py
fancy_source_query-0.1.5.dist-info/entry_points.txt
fancy_source_query-0.1.5.dist-info/WHEEL
fancy_source_query-0.1.5.dist-info/METADATA
fancy_source_query-0.1.5.dist-info/RECORD
