Metadata-Version: 2.1
Name: fancy_source_query
Version: 0.1.5
Summary: Intelligent tool to query source servers, with a cli interface and plugin integrates into nonebot.
License: MIT
Author-email: zombie110year <zombie110year@outlook.com>
Requires-Python: >=3.10,<4.0
Requires-Dist: exrex>=0.11.0
Requires-Dist: impaper>=0.1.6
Requires-Dist: nonebot-adapter-onebot>=2.2.2
Requires-Dist: nonebot2[fastapi]>=2.0.0rc3
Requires-Dist: pydantic>=1.10.7
Requires-Dist: steam[client]>=1.4.4
Requires-Dist: toml>=0.10.2
